AUTHORS
CHANGELOG.rst
LICENSE
MANIFEST.in
README
README.rst
requirements.txt
setup.cfg
setup.py
docs/CHANGELOG.rst
docs/CONTRIBUTING.rst
docs/LICENSE.rst
docs/README.rst
docs/conf.py
docs/index.rst
docs/html/index.html
tests/__init__.py
tests/test_sanity.py
tests/test_vnu_validator.py
tests/data/ways_to_do_it.html
vnu_validator/__init__.py
vnu_validator/__main__.py
vnu_validator/cli.py
vnu_validator/template.py
vnu_validator.egg-info/PKG-INFO
vnu_validator.egg-info/SOURCES.txt
vnu_validator.egg-info/dependency_links.txt
vnu_validator.egg-info/not-zip-safe
vnu_validator.egg-info/requires.txt
vnu_validator.egg-info/top_level.txt